{
    "authors": {
        "name": "Michael Shimniok",
        "url": "https://os.mbed.com/users/shimniok/"
    },
    "description": "Driver for National Semiconductor ADC128Sxxx family of analog to digital converters",
    "frameworks": "mbed",
    "keywords": [
        "adc",
        "driver",
        "BLE Bluetooth Low Energy BLE",
        "Bluetooth 4.0 Low Energy 4.0 ble HM-11 Hm11 Ble",
        "HC-SR04",
        "Microbit",
        "ultrasound"
    ],
    "name": "ADC128S",
    "platforms": "*",
    "repository": {
        "type": "hg",
        "url": "https://os.mbed.com/users/shimniok/code/ADC128S/"
    }
}