{
    "authors": {
        "name": "Y Tomohara",
        "url": "https://os.mbed.com/users/tomozh/"
    },
    "description": "AM2321 Temperature and Humidity Sensor mbed library",
    "examples": [
        "https://os.mbed.com/users/tomozh/code/AM2321_Example/",
        "https://os.mbed.com/users/mia_0032/code/mbed_vfd_thermometer/"
    ],
    "frameworks": "mbed",
    "keywords": [
        "I2C",
        "RHT",
        "sensor",
        "Si7013",
        "Si7020",
        "Si7021",
        "Silicon Labs",
        "silicon_labs",
        "siliconlabs",
        "Nucleo",
        "PCA9685",
        "pwm controller",
        "AT45DB081D",
        "AT45DB161D",
        "AT45DB321D",
        "EEPROM",
        "flash",
        "memory",
        "SPI",
        "http",
        "NET",
        "network",
        "webservice",
        "xml",
        "AM2321",
        "Humidity",
        "Temperature"
    ],
    "name": "AM2321",
    "platforms": "*",
    "repository": {
        "type": "hg",
        "url": "https://os.mbed.com/users/tomozh/code/AM2321/"
    }
}