{
    "authors": {
        "name": "Nicholas Herriot",
        "url": "https://os.mbed.com/users/nherriot/"
    },
    "description": "A tiny change to SKPanks GPS library to allow Ublox GPS modems to work.",
    "frameworks": "mbed",
    "keywords": [
        "4x4x4",
        "cube",
        "led",
        "mbeduino",
        "shield",
        "library",
        "rgb",
        "sensor",
        "TCS34725",
        "GPS",
        "ublox",
        "Vodafone"
    ],
    "name": "GPS",
    "platforms": "*",
    "repository": {
        "type": "hg",
        "url": "https://os.mbed.com/users/nherriot/code/GPS/"
    }
}