{
    "authors": {
        "name": "Flotsam",
        "url": "https://os.mbed.com/teams/Flotsam/"
    },
    "dependencies": [
        {
            "authors": {
                "url": "https://os.mbed.com/users/Flotsam"
            },
            "frameworks": "mbed",
            "name": "Adafruit_GSM",
            "url": "https://os.mbed.com/teams/Flotsam/code/Adafruit_GSM/"
        }
    ],
    "description": "GSM library for nucleo L152RE",
    "examples": [
        "https://os.mbed.com/teams/Flotsam/code/Full-Project/"
    ],
    "frameworks": "mbed",
    "keywords": [
        "checksum",
        "packets",
        "protocol",
        "Serial",
        "simple",
        "networking",
        "socket",
        "TCP",
        "UDP"
    ],
    "name": "GSM",
    "platforms": "*",
    "repository": {
        "type": "hg",
        "url": "https://os.mbed.com/teams/Flotsam/code/GSM/"
    }
}