{
    "authors": {
        "name": "CESAR CAZAL",
        "url": "https://os.mbed.com/users/cesarcazal/"
    },
    "description": "I2C libraries for the implementation of I2C communication in nRF51 based on I2C redbearlabs libraries",
    "examples": [
        "https://os.mbed.com/users/cesarcazal/code/I2C_Driver_Example/",
        "https://os.mbed.com/teams/TESIS-SATUROMETRICA/code/I2C_Driver_Example/",
        "https://os.mbed.com/users/kat123/code/nRF51822_SimpleControls/",
        "https://os.mbed.com/users/yesterday07/code/LastCode/",
        "https://os.mbed.com/teams/TESIS-SATUROMETRICA/code/MAX30100_FirstTry/",
        "https://os.mbed.com/users/Ferszt/code/MAX30100_FirstTry/",
        "https://os.mbed.com/teams/TESIS-SATUROMETRICA/code/MAX30100_V04/"
    ],
    "frameworks": "mbed",
    "keywords": [
        "DC",
        "driver",
        "H-bridge",
        "motor",
        "F042K6",
        "F103RB",
        "L152RE",
        "STM32F0",
        "STM32F1",
        "STM32L1",
        "USBDevice",
        "ARCH",
        "GPRS",
        "Seeed",
        "v2"
    ],
    "name": "I2C_Driver",
    "platforms": "*",
    "repository": {
        "type": "hg",
        "url": "https://os.mbed.com/users/cesarcazal/code/I2C_Driver/"
    }
}