{
    "authors": {
        "name": "ISR UC",
        "url": "https://os.mbed.com/users/ISR/"
    },
    "description": "Energy harvesting mobile robot.",
    "examples": [
        "https://os.mbed.com/users/AurelienBernier/code/Mapping/",
        "https://os.mbed.com/users/geotsam/code/VirtualForces_debug/",
        "https://os.mbed.com/users/geotsam/code/OneFileToRuleThemAll/",
        "https://os.mbed.com/users/Ludwigfr/code/VirtualForces_with_class/",
        "https://os.mbed.com/users/Ludwigfr/code/roboticLab_withclass/"
    ],
    "frameworks": "mbed",
    "keywords": [
        "f401",
        "mbed",
        "energy harvesting",
        "mobile robot",
        "MQTT"
    ],
    "name": "ISR_Mini-explorer",
    "platforms": "*",
    "repository": {
        "type": "hg",
        "url": "https://os.mbed.com/users/ISR/code/ISR_Mini-explorer/"
    }
}