{
    "authors": {
        "name": "Craig Evans",
        "url": "https://os.mbed.com/users/eencae/"
    },
    "description": "Analog joystick library",
    "examples": [
        "https://os.mbed.com/users/ll14c4p/code/GameProject_Prototype/",
        "https://os.mbed.com/users/jvfausto/code/Joystick/",
        "https://os.mbed.com/users/Jenny121/code/lcd205/",
        "https://os.mbed.com/users/Jenny121/code/Joystick205/",
        "https://os.mbed.com/users/el16dlc/code/el16dlc/",
        "https://os.mbed.com/teams/ELEC2645-201819/code/el16dlc/"
    ],
    "frameworks": "mbed",
    "keywords": "Joystick",
    "name": "Joystick",
    "platforms": "*",
    "repository": {
        "type": "hg",
        "url": "https://os.mbed.com/users/eencae/code/Joystick/"
    }
}