{
    "authors": {
        "name": "Hochschule München",
        "url": "https://os.mbed.com/users/HMFK03LST1/"
    },
    "description": "imu01c",
    "frameworks": "mbed",
    "keywords": [
        "HIH-4030",
        "Humidity",
        "sensor",
        "AD",
        "da",
        "MCP4921",
        "MCP4922",
        "Nucleo",
        "SPI",
        "UIT"
    ],
    "name": "LSM303D_imu",
    "platforms": "*",
    "repository": {
        "type": "hg",
        "url": "https://os.mbed.com/users/HMFK03LST1/code/LSM303D_imu/"
    }
}