{
    "authors": {
        "name": "Donatien Garnier",
        "url": "https://os.mbed.com/users/MiniTLS/"
    },
    "description": "HTTPS Client for MiniTLS-GPL",
    "examples": [
        "https://os.mbed.com/users/MiniTLS/code/MiniTLS-HTTPS-Example/"
    ],
    "frameworks": "mbed",
    "keywords": [
        "HD44780",
        "http",
        "SSL",
        "TLS",
        "BME280",
        "23K256",
        "23LC1024",
        "DMA",
        "FIFO",
        "RAM",
        "ring buffer",
        "SPI",
        "sram",
        "basicauth"
    ],
    "name": "MiniTLS-HTTPSClient",
    "platforms": "*",
    "repository": {
        "type": "hg",
        "url": "https://os.mbed.com/users/MiniTLS/code/MiniTLS-HTTPSClient/"
    }
}