{
    "authors": {
        "name": "Kevin Braun",
        "url": "https://os.mbed.com/users/loopsva/"
    },
    "description": "High resolution barometer and altimeter using i2c mode",
    "examples": "https://os",
    "frameworks": "mbed",
    "keywords": [
        "Altimeter",
        "barometer",
        "I2C",
        "ms5611",
        "bluetooth",
        "SDP",
        "display",
        "Seeedstudio",
        "TFT",
        "discovery",
        "ethernet",
        "Nucleo",
        "stm32",
        "STM32F746"
    ],
    "name": "ms5611",
    "platforms": "*",
    "repository": {
        "type": "hg",
        "url": "https://os.mbed.com/users/loopsva/code/ms5611/"
    }
}