{
    "authors": {
        "name": "J Daniel Martinez C",
        "url": "https://os.mbed.com/users/dan_cuspi/"
    },
    "description": "Audio usb",
    "examples": "https://os",
    "frameworks": "mbed",
    "keywords": [
        "Arduino mbed commands",
        "HD44780 LCD text custom char 16X2",
        "Ciseco",
        "SRF",
        "wireless",
        "XRF"
    ],
    "name": "MSCFileSystem",
    "platforms": "*",
    "repository": {
        "type": "hg",
        "url": "https://os.mbed.com/users/dan_cuspi/code/MSCFileSystem/"
    }
}