{
    "authors": {
        "name": "WIZnet",
        "url": "https://os.mbed.com/teams/WIZnet/"
    },
    "description": "NTP client.",
    "examples": [
        "https://os.mbed.com/teams/WIZnet/code/GT511C3_TimeStamp_WIZwiki-W7500/",
        "https://os.mbed.com/users/HarshaDRAGNEEL/code/Receive_RFID_Data_in_W750SR_and_send_RFI/"
    ],
    "frameworks": "mbed",
    "keywords": "NTP",
    "name": "NTPClient",
    "platforms": "*",
    "repository": {
        "type": "hg",
        "url": "https://os.mbed.com/teams/WIZnet/code/NTPClient/"
    }
}