{
    "authors": {
        "name": "Edward Wright",
        "url": "https://os.mbed.com/users/riteway66/"
    },
    "dependencies": [
        {
            "authors": "mbed official",
            "frameworks": "mbed",
            "name": "mbed"
        }
    ],
    "description": "Example program that uses the color LED of the mbed application shield (via arduino headers) with ST Nucleo board",
    "frameworks": "mbed",
    "keywords": [
        "color",
        "F103RB",
        "led",
        "mbed",
        "Nucleo",
        "shield",
        "ST"
    ],
    "name": "Nucleo_blink_color_led",
    "platforms": "*",
    "repository": {
        "type": "hg",
        "url": "https://os.mbed.com/users/riteway66/code/Nucleo_blink_color_led/"
    }
}