{
    "authors": {
        "name": "Phoenix Unicamp",
        "url": "https://os.mbed.com/users/PhoenixUnicamp/"
    },
    "description": "Basic Implementation of JSON.",
    "examples": "https://os",
    "frameworks": "mbed",
    "keywords": [
        "JSON",
        "LPC11U24",
        "LPC1768",
        "WDT",
        "LCD",
        "Serial",
        "TextDisplay",
        "TextDisplays",
        "TextLCD"
    ],
    "name": "oJSON",
    "platforms": "*",
    "repository": {
        "type": "hg",
        "url": "https://os.mbed.com/users/PhoenixUnicamp/code/oJSON/"
    }
}