{
    "authors": {
        "name": "InetrfaceProducts NXP",
        "url": "https://os.mbed.com/users/nxp_ip/"
    },
    "description": "Parallel bus (address 8 bit, data 8 bit) access sample using GPIO pins.",
    "examples": [
        "https://os.mbed.com/users/nxp_ip/code/mini_board_PCU9669_demo/",
        "https://os.mbed.com/users/nxp_ip/code/mini_board_PCU9669/"
    ],
    "frameworks": "mbed",
    "keywords": "parallel_bus",
    "name": "parallel_bus",
    "platforms": "*",
    "repository": {
        "type": "hg",
        "url": "https://os.mbed.com/users/nxp_ip/code/parallel_bus/"
    }
}