{
    "authors": {
        "name": "Wim Huiskamp",
        "url": "https://os.mbed.com/users/wim/"
    },
    "description": "Princeton PT6964 LED controller supports 4 Digits @ 13 Segments, 5 Digits @ 12 Segments, 6 Digits @ 11 Segments or 7 Digits @ 10 Segments. Also supports a scanned ...",
    "examples": [
        "https://os.mbed.com/users/wim/code/mbed_PT6964/"
    ],
    "frameworks": "mbed",
    "keywords": [
        "CM1628",
        "HT1628",
        "led",
        "PT6964 AIP1628",
        "SM1628"
    ],
    "name": "PT6964",
    "platforms": "*",
    "repository": {
        "type": "hg",
        "url": "https://os.mbed.com/users/wim/code/PT6964/"
    }
}