{
    "authors": {
        "name": "PHung Tung",
        "url": "https://os.mbed.com/users/phungductung/"
    },
    "dependencies": [
        {
            "authors": "不韋 呂",
            "frameworks": "mbed",
            "name": "SDFileSystem_Warning_Fixed"
        }
    ],
    "description": "SPKT",
    "examples": [
        "https://os.mbed.com/users/phungductung/code/DISCO-F746_WAV_PLAYER/",
        "https://os.mbed.com/users/fundokukiri/code/WAV/"
    ],
    "frameworks": "mbed",
    "keywords": "SPKT",
    "name": "SD_PlayerSkeleton",
    "platforms": "*",
    "repository": {
        "type": "hg",
        "url": "https://os.mbed.com/users/phungductung/code/SD_PlayerSkeleton/"
    }
}