{
    "authors": {
        "name": "Chris Hamilton",
        "url": "https://os.mbed.com/users/chamilton333/"
    },
    "dependencies": [
        {
            "authors": "Simon Ford",
            "frameworks": "mbed",
            "name": "Servo"
        }
    ],
    "description": "---",
    "frameworks": "mbed",
    "keywords": "Servo",
    "name": "Servo",
    "platforms": "*",
    "repository": {
        "type": "hg",
        "url": "https://os.mbed.com/users/chamilton333/code/Servo/"
    }
}