{
    "authors": {
        "name": "Jake L",
        "url": "https://os.mbed.com/users/jelord/"
    },
    "description": "Line 48 commented out",
    "examples": "https://os",
    "frameworks": "mbed",
    "keywords": [
        "Mouse",
        "optical",
        "sensor",
        "edutech",
        "EPB",
        "EPB_TextLCD",
        "LCD"
    ],
    "name": "SI1145",
    "platforms": "*",
    "repository": {
        "type": "hg",
        "url": "https://os.mbed.com/users/jelord/code/SI1145/"
    }
}