{
    "authors": {
        "name": "Libor GECNUK",
        "url": "https://os.mbed.com/users/liborgecnuk/"
    },
    "description": "SCLD peripheral of the KL46Z - with sign \"-\" just for USB Academy",
    "examples": [
        "https://os.mbed.com/users/wue/code/KL46Z-Lab2_lodz/",
        "https://os.mbed.com/users/Osator/code/KL46Z-Lab2_fullll/",
        "https://os.mbed.com/users/zochmen/code/KL46Z-Lab2_szkolenie/",
        "https://os.mbed.com/users/wue/code/kL46Z-Lab3-lodz/",
        "https://os.mbed.com/users/bclaus/code/RCSailboatController/"
    ],
    "frameworks": "mbed",
    "keywords": [
        "audio",
        "files",
        "I2C",
        "I2S",
        "playing",
        "RS labboard",
        "TLV320",
        "wav",
        "ILI9341",
        "TFT",
        "xml",
        "FRDM",
        "KL46",
        "kl46z",
        "LCD",
        "SLCD"
    ],
    "name": "SLCD-",
    "platforms": "*",
    "repository": {
        "type": "hg",
        "url": "https://os.mbed.com/users/liborgecnuk/code/SLCD-/"
    }
}