{
    "authors": {
        "name": "Shinichiro Nakamura",
        "url": "https://os.mbed.com/users/shintamainjp/"
    },
    "description": "SuperTweet interface driver classes.",
    "examples": [
        "https://os.mbed.com/users/shintamainjp/code/SuperTweet_TestProgram/",
        "https://os.mbed.com/users/shintamainjp/code/StarBoardOrangeExpansion1/",
        "https://os.mbed.com/users/botdream/code/GSL_04-Network_Twitter/"
    ],
    "frameworks": "mbed",
    "keywords": "SuperTweet",
    "name": "SuperTweet",
    "platforms": "*",
    "repository": {
        "type": "hg",
        "url": "https://os.mbed.com/users/shintamainjp/code/SuperTweet/"
    }
}