{
    "authors": {
        "name": "Grupo Fiuba",
        "url": "https://os.mbed.com/users/Fiuba/"
    },
    "description": "This library creates the interface to operate the TLC5940. This device manages 16 PWM outputs.",
    "frameworks": "mbed",
    "keywords": [
        "3axis",
        "accelorometer",
        "AnalogIn",
        "sensor",
        "led",
        "pwm",
        "tlc5940",
        "CRC",
        "CRC32"
    ],
    "name": "tlc5940",
    "platforms": "*",
    "repository": {
        "type": "hg",
        "url": "https://os.mbed.com/users/Fiuba/code/tlc5940/"
    }
}